pollute/__init__.py
pollute-1.0.2.dist-info/top_level.txt
pollute-1.0.2.dist-info/METADATA
pollute-1.0.2.dist-info/DESCRIPTION.rst
pollute-1.0.2.dist-info/metadata.json
pollute-1.0.2.dist-info/WHEEL
pollute-1.0.2.dist-info/RECORD
